axis_sdk/__init__.py
axis_sdk/protocols/__init__.py
axis_sdk/protocols/agent.py
axis_sdk/protocols/ledger.py
axis_sdk/protocols/orchestrator.py
axis_sdk/protocols/reasoning.py
axis_sdk/protocols/runtime.py
axis_sdk/protocols/skills.py
axis_sdk/protocols/telemetry.py
axis_sdk/types/__init__.py
axis_sdk/types/agent.py
axis_sdk/types/reasoning.py
axis_sdk-0.3.1.dist-info/licenses/LICENSE
axis_sdk-0.3.1.dist-info/METADATA
axis_sdk-0.3.1.dist-info/WHEEL
axis_sdk-0.3.1.dist-info/top_level.txt
axis_sdk-0.3.1.dist-info/RECORD
