Metadata-Version: 2.4
Name: axis-sdk
Version: 0.3.1
Summary: AXIS SDK - Zero-dependency protocol and type definitions for AXIS agents
Author-email: Emily Veiga <emily@lumpi.ai>
License: MIT
Project-URL: Homepage, https://github.com/emilyveigaai/axis-sdk
Project-URL: Documentation, https://github.com/emilyveigaai/axis-sdk#readme
Project-URL: Repository, https://github.com/emilyveigaai/axis-sdk
Project-URL: Issues, https://github.com/emilyveigaai/axis-sdk/issues
Requires-Python: >=3.10
License-File: LICENSE
Requires-Dist: pydantic>=2.0.0
Provides-Extra: dev
Requires-Dist: pytest>=7.0.0; extra == "dev"
Requires-Dist: pytest-cov>=4.0.0; extra == "dev"
Requires-Dist: black>=23.0.0; extra == "dev"
Requires-Dist: ruff>=0.1.0; extra == "dev"
Requires-Dist: mypy>=1.0.0; extra == "dev"
Dynamic: license-file
